{
  "total": 4,
  "rows": [
    {
      "_parentId": "",
      "ID": "1",
      "factory_name": "九江首创"
    },
    {
      "_parentId": "1",
      "ID": "11",
      "factory_name": "一厂",
      "a1": "100",
      "a2": "100",
      "a3": "100",
      "a4": "100",
      "a5": "100",
      "a6": "100",
      "a7": "100",
      "a8": "100",
      "b1": "100",
      "b2": "100",
      "b3": "100",
      "b4": "100",
      "c1": "100",
      "c2": "100",
      "c3": "100",
      "c4": "100",
      "d1": "100"
    },
    {
      "_parentId": "1",
      "ID": "12",
      "factory_name": "二厂",
      "a1": "100",
      "a2": "100",
      "a3": "100",
      "a4": "100",
      "a5": "100",
      "a6": "100",
      "a7": "100",
      "a8": "100",
      "b1": "100",
      "b2": "100",
      "b3": "100",
      "b4": "100",
      "c1": "100",
      "c2": "100",
      "c3": "100",
      "c4": "100",
      "d1": "100"
    },
    {
      "_parentId": "1",
      "ID": "13",
      "factory_name": "三厂",
      "a1": "100",
      "a2": "100",
      "a3": "100",
      "a4": "100",
      "a5": "100",
      "a6": "100",
      "a7": "100",
      "a8": "100",
      "b1": "100",
      "b2": "100",
      "b3": "100",
      "b4": "100",
      "c1": "100",
      "c2": "100",
      "c3": "100",
      "c4": "100",
      "d1": "100"
    }
  ]
}
